hurst/__init__.py
hurst-0.0.4.dist-info/METADATA
hurst-0.0.4.dist-info/RECORD
hurst-0.0.4.dist-info/WHEEL
hurst-0.0.4.dist-info/top_level.txt
