Metadata-Version: 2.1
Name: hurst
Version: 0.0.4
Summary: Hurst exponent evaluation and R/S-analysis
Home-page: https://github.com/Mottl/hurst
Author: Dmitry Mottl
Author-email: dmitry.mottl@gmail.com
License: MIT
Keywords: hurst fractal econometrics time-series
Platform: UNKNOWN
Classifier: Programming Language :: Python :: 2.7
Classifier: Programming Language :: Python :: 3
Classifier: Programming Language :: Python :: 3.4
Classifier: Programming Language :: Python :: 3.5
Classifier: Programming Language :: Python :: 3.6
Classifier: License :: OSI Approved :: MIT License
Classifier: Operating System :: OS Independent
Classifier: Topic :: Scientific/Engineering :: Mathematics
Requires-Dist: pandas (>=0.18)
Requires-Dist: numpy (>=1.10)
